gcl_sdk/__init__.py
gcl_sdk/version.py
gcl_sdk/agents/__init__.py
gcl_sdk/agents/universal/__init__.py
gcl_sdk/agents/universal/constants.py
gcl_sdk/agents/universal/utils.py
gcl_sdk/agents/universal/clients/__init__.py
gcl_sdk/agents/universal/clients/backend/__init__.py
gcl_sdk/agents/universal/clients/backend/base.py
gcl_sdk/agents/universal/clients/backend/core.py
gcl_sdk/agents/universal/clients/backend/db.py
gcl_sdk/agents/universal/clients/backend/exceptions.py
gcl_sdk/agents/universal/clients/backend/rest.py
gcl_sdk/agents/universal/clients/http/__init__.py
gcl_sdk/agents/universal/clients/http/orch.py
gcl_sdk/agents/universal/clients/http/status.py
gcl_sdk/agents/universal/clients/orch/__init__.py
gcl_sdk/agents/universal/clients/orch/base.py
gcl_sdk/agents/universal/clients/orch/db.py
gcl_sdk/agents/universal/clients/orch/exceptions.py
gcl_sdk/agents/universal/clients/orch/http.py
gcl_sdk/agents/universal/cmd/__init__.py
gcl_sdk/agents/universal/cmd/scheduler.py
gcl_sdk/agents/universal/cmd/universal_agent.py
gcl_sdk/agents/universal/cmd/universal_agent_db_back.py
gcl_sdk/agents/universal/dm/__init__.py
gcl_sdk/agents/universal/dm/models.py
gcl_sdk/agents/universal/drivers/base.py
gcl_sdk/agents/universal/drivers/core.py
gcl_sdk/agents/universal/drivers/direct.py
gcl_sdk/agents/universal/drivers/dummy.py
gcl_sdk/agents/universal/drivers/exceptions.py
gcl_sdk/agents/universal/drivers/guest.py
gcl_sdk/agents/universal/drivers/lb.py
gcl_sdk/agents/universal/drivers/meta.py
gcl_sdk/agents/universal/drivers/render.py
gcl_sdk/agents/universal/drivers/service.py
gcl_sdk/agents/universal/drivers/ssh_key.py
gcl_sdk/agents/universal/orch_api/__init__.py
gcl_sdk/agents/universal/orch_api/controllers.py
gcl_sdk/agents/universal/orch_api/routes.py
gcl_sdk/agents/universal/services/__init__.py
gcl_sdk/agents/universal/services/agent.py
gcl_sdk/agents/universal/services/builder.py
gcl_sdk/agents/universal/services/common.py
gcl_sdk/agents/universal/services/scheduler.py
gcl_sdk-1.3.0.dist-info/licenses/AUTHORS
gcl_sdk-1.3.0.dist-info/licenses/LICENSE
gcl_sdk-1.3.0.dist-info/METADATA
gcl_sdk-1.3.0.dist-info/WHEEL
gcl_sdk-1.3.0.dist-info/entry_points.txt
gcl_sdk-1.3.0.dist-info/pbr.json
gcl_sdk-1.3.0.dist-info/top_level.txt
gcl_sdk-1.3.0.dist-info/RECORD
