Metadata-Version: 2.4
Name: gcl_sdk
Version: 1.3.0
Summary: The Genesis Core SDK
Home-page: https://github.com/infraguys/gcl_sdk/
Author: Genesis Corporation
Author-email: eugene@frolov.net.ru
Classifier: Intended Audience :: Developers
Classifier: License :: OSI Approved :: Apache Software License
Classifier: Operating System :: POSIX :: Linux
Classifier: Programming Language :: Python
Classifier: Programming Language :: Python :: 3
Classifier: Programming Language :: Python :: 3.8
Classifier: Programming Language :: Python :: 3.10
Classifier: Programming Language :: Python :: 3.11
Classifier: Programming Language :: Python :: 3.12
Classifier: Programming Language :: Python :: 3.13
License-File: LICENSE
License-File: AUTHORS
Requires-Dist: pbr<=5.8.1,>=1.10.0
Requires-Dist: oslo.config<10.0.0,>=3.22.2
Requires-Dist: importlib-metadata<7.0.0,>=6.8.0
Requires-Dist: restalchemy<16.0.0,>=15.0.1
Requires-Dist: gcl_iam<2.0.0,>=1.0.0
Requires-Dist: gcl_looper<2.0.0,>=1.0.1
Requires-Dist: bjoern>=3.2.2
Requires-Dist: izulu<1.0.0,>=0.50.0
Requires-Dist: renameat2<1.0.0,>=0.4.4
Requires-Dist: xxhash<4.0.0,>=3.5.0
Dynamic: author
Dynamic: author-email
Dynamic: classifier
Dynamic: description
Dynamic: home-page
Dynamic: license-file
Dynamic: requires-dist
Dynamic: summary
